[
    {
        "name": "Fone de Ouvido Bluetooth 5.4 TWS Intra Auricular som Anti ruído Original Basike",
        "category": "fone",
        "brand": "Basike",
        "price": 163.0,
        "product_url": "https://www.magazineluiza.com.br/fone-de-ouvido-bluetooth-5-4-tws-intra-auricular-som-anti-ruido-original-basike/p/hec0219e53/ea/fobt/",
        "rating": null,
        "in_stock": true,
        "extracted_at": "2026-02-11T13:02:04-03:00"
    },
    {
        "name": "Fones De Ouvido Bluetooth Sem Fio Lenovo LP40 Com Controle Por Toque, Headset Esportivo Estéreo Para",
        "category": "fone",
        "brand": "Lenovo",
        "price": 51.59,
        "product_url": "https://www.magazineluiza.com.br/fones-de-ouvido-bluetooth-sem-fio-lenovo-lp40-com-controle-por-toque-headset-esportivo-estereo-para/p/cgj4509b17/ea/fobt/",
        "rating": null,
        "in_stock": true,
        "extracted_at": "2026-02-11T13:02:06-03:00"
    },
    {
        "name": "Fone de Ouvido Headset Gamer JBL Quantum 200 Preto",
        "category": "fone",
        "brand": "JBL",
        "price": 259.0,
        "product_url": "https://www.magazineluiza.com.br/fone-de-ouvido-headset-gamer-jbl-quantum-200-preto/p/jgc8296ak4/ea/hdga/",
        "rating": 4.9,
        "in_stock": true,
        "extracted_at": "2026-02-11T13:02:08-03:00"
    },
    {
        "name": "Fone de Ouvido Sem Fio Gamer Sony Pulse Explore, Bluetooth, Cancelamento de Ruído, PC, PS5 e Dispositivo Móvel Branco - CFI-ZWE1L",
        "category": "fone",
        "brand": "Sony",
        "price": 1247.0,
        "product_url": "https://www.magazineluiza.com.br/fone-de-ouvido-sem-fio-gamer-sony-pulse-explore-bluetooth-cancelamento-de-ruido-pc-ps5-e-dispositivo-movel-branco-cfi-zwe1l/p/gef7hb8kk9/ea/fngm/",
        "rating": 5.0,
        "in_stock": true,
        "extracted_at": "2026-02-11T13:02:10-03:00"
    },
    {
        "name": "Fone XT80 Lenovo Sport Lançamento",
        "category": "fone",
        "brand": "Lenovo",
        "price": 129.0,
        "product_url": "https://www.magazineluiza.com.br/fone-xt80-lenovo-sport-lancamento/p/dejjeh6ed3/ea/fobt/",
        "rating": 4.4,
        "in_stock": true,
        "extracted_at": "2026-02-11T13:02:12-03:00"
    },
    {
        "name": "Fone Qcy T29 Bluetooth 5.3 IPX4 Cancelamento Enc",
        "category": "fone",
        "brand": "QCY",
        "price": 155.57,
        "product_url": "https://www.magazineluiza.com.br/fone-qcy-t29-bluetooth-5-3-ipx4-cancelamento-enc/p/ka0a0ejea4/ea/fobt/",
        "rating": 4.76,
        "in_stock": true,
        "extracted_at": "2026-02-11T13:02:14-03:00"
    },
    {
        "name": "Fones De Ouvido Sem Fio Bluetooth 5.3 Lenovo GM2 pro 9D Estéreo Com Microfone 6 Fones De Ouvido",
        "category": "fone",
        "brand": "Lenovo",
        "price": 37.1,
        "product_url": "https://www.magazineluiza.com.br/fones-de-ouvido-sem-fio-bluetooth-5-3-lenovo-gm2-pro-9d-estereo-com-microfone-6-fones-de-ouvido/p/dhja7210g2/ea/eafn/",
        "rating": 5.0,
        "in_stock": true,
        "extracted_at": "2026-02-11T13:02:17-03:00"
    },
    {
        "name": "Fone de Ouvido Samsung Buds3 FE com Microfone Cancelamento Ativo de Ruído Esportivo Intra-auricular True Wireless Preto",
        "category": "fone",
        "brand": "Samsung",
        "price": 699.0,
        "product_url": "https://www.magazineluiza.com.br/fone-de-ouvido-samsung-buds3-fe-com-microfone-cancelamento-ativo-de-ruido-esportivo-intra-auricular-true-wireless-preto/p/240580200/ea/eafn/",
        "rating": 5.0,
        "in_stock": true,
        "extracted_at": "2026-02-11T13:02:19-03:00"
    },
    {
        "name": "Fone de Ouvido Sem Fio JBL Tune Buds 2, Bluetooth 5.3, Branco - 28913851",
        "category": "fone",
        "brand": "JBL",
        "price": 443.33,
        "product_url": "https://www.magazineluiza.com.br/fone-de-ouvido-sem-fio-jbl-tune-buds-2-bluetooth-5-3-branco-28913851/p/ehd9600804/ea/fobt/",
        "rating": null,
        "in_stock": true,
        "extracted_at": "2026-02-11T13:02:22-03:00"
    },
    {
        "name": "Fone de Ouvido Esportivo JBL Endurance Race 2, Bluetooth: 5.3, Azul - 28913818",
        "category": "fone",
        "brand": "JBL",
        "price": 379.0,
        "product_url": "https://www.magazineluiza.com.br/fone-de-ouvido-esportivo-jbl-endurance-race-2-bluetooth-5-3-azul-28913818/p/bdf50cb871/ea/fobt/",
        "rating": 4.83,
        "in_stock": true,
        "extracted_at": "2026-02-11T13:02:24-03:00"
    },
    {
        "name": "Fone de Ouvido Sem Fio JBL Tune 520BT, Bluetooth, com Microfone, Branco - JBLT520BTWHT",
        "category": "fone",
        "brand": "JBL",
        "price": 179.0,
        "product_url": "https://www.magazineluiza.com.br/fone-de-ouvido-sem-fio-jbl-tune-520bt-bluetooth-com-microfone-branco-jblt520btwht/p/da2hjkc24a/ea/fobt/",
        "rating": 4.81,
        "in_stock": true,
        "extracted_at": "2026-02-11T13:02:26-03:00"
    },
    {
        "name": "Fone de Ouvido C3Tech Comfort com Microfone, Conexão P2, com Controle de Volume e Almofada de Espuma, Preto - PH-60BK - C3 tech",
        "category": "fone",
        "brand": "C3Tech",
        "price": 39.0,
        "product_url": "https://www.magazineluiza.com.br/fone-de-ouvido-c3tech-comfort-com-microfone-conexao-p2-com-controle-de-volume-e-almofada-de-espuma-preto-ph-60bk-c3-tech/p/fg989jfje7/ea/hecf/",
        "rating": 4.3,
        "in_stock": true,
        "extracted_at": "2026-02-11T13:02:28-03:00"
    },
    {
        "name": "Fone de Ouvido com Fio USBC Compatível com iPhone 15 15Pro 15ProMax 16 16e 16Pro 16ProMax 17 17Pro 17ProMax 17Air - LELONG/HMASTON/ONEX",
        "category": "fone",
        "brand": null,
        "price": 85.0,
        "product_url": "https://www.magazineluiza.com.br/fone-de-ouvido-com-fio-usbc-compativel-com-iphone-15-15pro-15promax-16-16e-16pro-16promax-17-17pro-17promax-17air-lelong-hmaston-onex/p/ce8jeh7kce/ea/fobt/",
        "rating": 5.0,
        "in_stock": true,
        "extracted_at": "2026-02-11T13:02:30-03:00"
    },
    {
        "name": "Fone de ouvido Sem Fio Bluetooth Motorola Moto Buds Bass Cancelamento de Ruído Ativo, Som espacial e até 43h de bateria",
        "category": "fone",
        "brand": "Motorola",
        "price": 359.1,
        "product_url": "https://www.magazineluiza.com.br/fone-de-ouvido-sem-fio-bluetooth-motorola-moto-buds-bass-cancelamento-de-ruido-ativo-som-espacial-e-ate-43h-de-bateria/p/da5db5h43k/ea/focf/",
        "rating": 5.0,
        "in_stock": true,
        "extracted_at": "2026-02-11T13:02:33-03:00"
    },
    {
        "name": "Fones De Ouvido Tradutores AI Com Tradução Em Tempo Real Para 144 Idiomas Para Viagens E Negócios - DAMORE",
        "category": "fone",
        "brand": null,
        "price": 38.37,
        "product_url": "https://www.magazineluiza.com.br/fones-de-ouvido-tradutores-ai-com-traducao-em-tempo-real-para-144-idiomas-para-viagens-e-negocios-damore/p/djk7304k3f/ea/fobt/",
        "rating": null,
        "in_stock": true,
        "extracted_at": "2026-02-11T13:02:35-03:00"
    },
    {
        "name": "Fone de Ouvido Bluetooth sem Fio Headset Anti-ruído Original Inova",
        "category": "fone",
        "brand": "Inova",
        "price": 67.85,
        "product_url": "https://www.magazineluiza.com.br/fone-de-ouvido-bluetooth-sem-fio-headset-anti-ruido-original-inova/p/fe23eca92g/ea/hdgm/",
        "rating": 4.56,
        "in_stock": true,
        "extracted_at": "2026-02-11T13:02:37-03:00"
    },
    {
        "name": "Fone QCY Ailybuds E10 HiRes LDAC",
        "category": "fone",
        "brand": "QCY",
        "price": 158.54,
        "product_url": "https://www.magazineluiza.com.br/fone-qcy-ailybuds-e10-hires-ldac/p/fhd1cbe23h/ea/fobt/",
        "rating": 5.0,
        "in_stock": true,
        "extracted_at": "2026-02-11T13:02:40-03:00"
    },
    {
        "name": "Fone De Ouvido Bluetooth Orelha Gatinho Infantil Led Sem Fio - Laves",
        "category": "fone",
        "brand": null,
        "price": 41.0,
        "product_url": "https://www.magazineluiza.com.br/fone-de-ouvido-bluetooth-orelha-gatinho-infantil-led-sem-fio-laves/p/hca62f3dh8/ea/fobt/",
        "rating": 3.3,
        "in_stock": true,
        "extracted_at": "2026-02-11T13:02:42-03:00"
    },
    {
        "name": "Fone Bluetooth QCY HT08 Melobuds Pro ANC 5.3 com Conexão Multiponto",
        "category": "fone",
        "brand": "QCY",
        "price": 323.57,
        "product_url": "https://www.magazineluiza.com.br/fone-bluetooth-qcy-ht08-melobuds-pro-anc-5-3-com-conexao-multiponto/p/fga3k4gc67/ea/fobt/",
        "rating": 4.64,
        "in_stock": true,
        "extracted_at": "2026-02-11T13:02:45-03:00"
    },
    {
        "name": "Fone de Ouvido Sem Fio JBL Tune 520BT, Bluetooth, com Microfone, Azul - JBLT520BTBLU",
        "category": "fone",
        "brand": "JBL",
        "price": 179.0,
        "product_url": "https://www.magazineluiza.com.br/fone-de-ouvido-sem-fio-jbl-tune-520bt-bluetooth-com-microfone-azul-jblt520btblu/p/bhejdc143f/ea/fobt/",
        "rating": 4.79,
        "in_stock": true,
        "extracted_at": "2026-02-11T13:02:47-03:00"
    },
    {
        "name": "Fone de Ouvido Bluetooth Samsung Buds Core com Microfone Cancelamento de Ruído Esportivo Intra-auricular True Wireless Branco",
        "category": "fone",
        "brand": "Samsung",
        "price": 259.0,
        "product_url": "https://www.magazineluiza.com.br/fone-de-ouvido-bluetooth-samsung-buds-core-com-microfone-cancelamento-de-ruido-esportivo-intra-auricular-true-wireless-branco/p/240580400/ea/eafn/",
        "rating": 4.77,
        "in_stock": true,
        "extracted_at": "2026-02-11T13:02:49-03:00"
    },
    {
        "name": "Fone de Ouvido Bluetooth Baseus Bowie MZ10 com ANC Cancelamento de ruído ativo, Multiponto, App Personalizável e 20h de Bateria",
        "category": "fone",
        "brand": "Baseus",
        "price": 153.0,
        "product_url": "https://www.magazineluiza.com.br/fone-de-ouvido-bluetooth-baseus-bowie-mz10-com-anc-cancelamento-de-ruido-ativo-multiponto-app-personalizavel-e-20h-de-bateria/p/jha1k0kd1h/ea/fobt/",
        "rating": null,
        "in_stock": true,
        "extracted_at": "2026-02-11T13:02:51-03:00"
    },
    {
        "name": "Fone de Ouvido Sem Fio QCY T13 TWS 4 Mics Controle Por Toque e Bluetooth 5.1",
        "category": "fone",
        "brand": "QCY",
        "price": 175.52,
        "product_url": "https://www.magazineluiza.com.br/fone-de-ouvido-sem-fio-qcy-t13-tws-4-mics-controle-por-toque-e-bluetooth-5-1/p/jffedakfgh/ea/fobt/",
        "rating": 4.75,
        "in_stock": true,
        "extracted_at": "2026-02-11T13:02:53-03:00"
    },
    {
        "name": "Fone QCY E20 Ailybuds ANC Bluetooth 5.4",
        "category": "fone",
        "brand": "QCY",
        "price": 186.67,
        "product_url": "https://www.magazineluiza.com.br/fone-qcy-e20-ailybuds-anc-bluetooth-5-4/p/cg57j10160/ea/fobt/",
        "rating": 3.6,
        "in_stock": true,
        "extracted_at": "2026-02-11T13:02:55-03:00"
    },
    {
        "name": "Fone de Ouvido com Fio Lightning Compatível com iPhone 7 8 X XS SR 11 12 13 14 Pro Max - Tx - Original",
        "category": "fone",
        "brand": null,
        "price": 119.0,
        "product_url": "https://www.magazineluiza.com.br/fone-de-ouvido-com-fio-lightning-compativel-com-iphone-7-8-x-xs-sr-11-12-13-14-pro-max-tx-original/p/aba0j1f605/ea/focf/",
        "rating": 3.0,
        "in_stock": true,
        "extracted_at": "2026-02-11T13:02:58-03:00"
    },
    {
        "name": "Fone de Ouvido Sem Fio Bluetooth Samsung Buds Core com Microfone Cancelamento de Ruído True Wireless Preto",
        "category": "fone",
        "brand": "SAMSUNG",
        "price": 244.9,
        "product_url": "https://www.magazineluiza.com.br/fone-de-ouvido-sem-fio-bluetooth-samsung-buds-core-com-microfone-cancelamento-de-ruido-true-wireless-preto/p/jkg85kbd00/ea/eafn/",
        "rating": 4.79,
        "in_stock": true,
        "extracted_at": "2026-02-11T13:03:00-03:00"
    },
    {
        "name": "Fone De Ouvido Bluetooth Cancelamento De Ruído Som Imersivo Microfone - Basike",
        "category": "fone",
        "brand": "Basike",
        "price": 289.9,
        "product_url": "https://www.magazineluiza.com.br/fone-de-ouvido-bluetooth-cancelamento-de-ruido-som-imersivo-microfone-basike/p/ee119hejka/ea/fobt/",
        "rating": null,
        "in_stock": true,
        "extracted_at": "2026-02-11T13:03:03-03:00"
    },
    {
        "name": "Fones De Ouvido Sem Fio Bluetooth 5.3 Lenovo TH30, Headset Dobrável Para Jogos Com Microfone, Fones",
        "category": "fone",
        "brand": "Lenovo",
        "price": 102.0,
        "product_url": "https://www.magazineluiza.com.br/fones-de-ouvido-sem-fio-bluetooth-5-3-lenovo-th30-headset-dobravel-para-jogos-com-microfone-fones/p/bb47626khh/ea/fngm/",
        "rating": null,
        "in_stock": true,
        "extracted_at": "2026-02-11T13:03:05-03:00"
    },
    {
        "name": "Fone de Ouvido Bluetooth Cancelamento de Ruído Bateria Longa Duração - Basike",
        "category": "fone",
        "brand": "Basike",
        "price": 206.0,
        "product_url": "https://www.magazineluiza.com.br/fone-de-ouvido-bluetooth-cancelamento-de-ruido-bateria-longa-duracao-basike/p/ad72809e48/ea/fobt/",
        "rating": null,
        "in_stock": true,
        "extracted_at": "2026-02-11T13:03:08-03:00"
    },
    {
        "name": "Fone De Ouvido TWS Bluetooth 5.3 Sem Fio Com Microfone Integrado, Cancelamento De Ruído, Compatibilidade Universal, Ideal Para Academia E Trabal - Univerza Produtos",
        "category": "fone",
        "brand": null,
        "price": 132.9,
        "product_url": "https://www.magazineluiza.com.br/fone-de-ouvido-tws-bluetooth-5-3-sem-fio-com-microfone-integrado-cancelamento-de-ruido-compatibilidade-universal-ideal-para-academia-e-trabal-univerza-produtos/p/gah81ec879/ea/fngm/",
        "rating": 4.4,
        "in_stock": true,
        "extracted_at": "2026-02-11T13:03:10-03:00"
    },
    {
        "name": "Fones De Ouvido Sem Fio Para Jogos V9 pro MCHOSE, Música E Esports, Microfone Com Redução De Ruído",
        "category": "fone",
        "brand": "MCHOSE",
        "price": 269.82,
        "product_url": "https://www.magazineluiza.com.br/fones-de-ouvido-sem-fio-para-jogos-v9-pro-mchose-musica-e-esports-microfone-com-reducao-de-ruido/p/bhkee6gb2g/ea/fngm/",
        "rating": 5.0,
        "in_stock": true,
        "extracted_at": "2026-02-11T13:03:12-03:00"
    },
    {
        "name": "Fone De Ouvido Baseus Sem Fio Bowie E18 Bluetooth 5.3",
        "category": "fone",
        "brand": "Baseus",
        "price": 110.07,
        "product_url": "https://www.magazineluiza.com.br/fone-de-ouvido-baseus-sem-fio-bowie-e18-bluetooth-5-3/p/fck408bfg2/ea/hebl/",
        "rating": 3.5,
        "in_stock": true,
        "extracted_at": "2026-02-11T13:03:15-03:00"
    },
    {
        "name": "Fones De Ouvido Tradutores De IA Em 144 Idiomas Bluetooth 5.3 Sem Fio Com Cancelamento De Ruído Em",
        "category": "fone",
        "brand": "iHseno",
        "price": 94.97,
        "product_url": "https://www.magazineluiza.com.br/fones-de-ouvido-tradutores-de-ia-em-144-idiomas-bluetooth-5-3-sem-fio-com-cancelamento-de-ruido-em-ihseno/p/dg1833gk6h/ea/fobt/",
        "rating": 5.0,
        "in_stock": true,
        "extracted_at": "2026-02-11T13:03:18-03:00"
    },
    {
        "name": "Fone De Ouvido Kz Edx Pro Sem Microfone Intra Auricular",
        "category": "fone",
        "brand": "Kz",
        "price": 113.0,
        "product_url": "https://www.magazineluiza.com.br/fone-de-ouvido-kz-edx-pro-sem-microfone-intra-auricular/p/ff14hkc311/ea/focf/",
        "rating": 5.0,
        "in_stock": true,
        "extracted_at": "2026-02-11T13:03:20-03:00"
    },
    {
        "name": "Apple AirPods Pro 3",
        "category": "fone",
        "brand": "Apple",
        "price": 2339.1,
        "product_url": "https://www.magazineluiza.com.br/apple-airpods-pro-3/p/240593200/ea/eafn/",
        "rating": 5.0,
        "in_stock": true,
        "extracted_at": "2026-02-11T13:03:22-03:00"
    },
    {
        "name": "Fone De Ouvido Sem Fio Baseus Bowie E20 Bluetooth 5.3",
        "category": "fone",
        "brand": "Baseus",
        "price": 143.0,
        "product_url": "https://www.magazineluiza.com.br/fone-de-ouvido-sem-fio-baseus-bowie-e20-bluetooth-5-3/p/gb65j3bd2e/ea/focf/",
        "rating": 4.5,
        "in_stock": true,
        "extracted_at": "2026-02-11T13:03:25-03:00"
    },
    {
        "name": "Fone de Ouvido Gamer HyperX Cloud Earbuds II, Com Microfone, Vermelho - 705L8AA - Hyper X",
        "category": "fone",
        "brand": "HyperX",
        "price": 129.0,
        "product_url": "https://www.magazineluiza.com.br/fone-de-ouvido-gamer-hyperx-cloud-earbuds-ii-com-microfone-vermelho-705l8aa-hyper-x/p/geb0hjka1e/ea/fngm/",
        "rating": 4.7,
        "in_stock": true,
        "extracted_at": "2026-02-11T13:03:27-03:00"
    },
    {
        "name": "Fone de Ouvido JBL Tune 720BT, Bluetooth, Bateria de até 76 Horas, Branco - JBLT720BTWHT",
        "category": "fone",
        "brand": "JBL",
        "price": 332.22,
        "product_url": "https://www.magazineluiza.com.br/fone-de-ouvido-jbl-tune-720bt-bluetooth-bateria-de-ate-76-horas-branco-jblt720btwht/p/bj508205e4/ea/hebl/",
        "rating": 4.6,
        "in_stock": true,
        "extracted_at": "2026-02-11T13:03:29-03:00"
    },
    {
        "name": "Fone Bluetooth Xiaomi Redmi Buds 6 Play, sem fio, Bluetooth 5.4, bateria de 36 horas Preto",
        "category": "fone",
        "brand": "Xiaomi",
        "price": 109.0,
        "product_url": "https://www.magazineluiza.com.br/fone-bluetooth-xiaomi-redmi-buds-6-play-sem-fio-bluetooth-5-4-bateria-de-36-horas-preto/p/ckf8k37b2a/ea/fobt/",
        "rating": null,
        "in_stock": true,
        "extracted_at": "2026-02-11T13:03:32-03:00"
    },
    {
        "name": "Fones de Ouvido Sem Fio PULSE Explore PS5 - SONY",
        "category": "fone",
        "brand": "Sony",
        "price": 1099.0,
        "product_url": "https://www.magazineluiza.com.br/fones-de-ouvido-sem-fio-pulse-explore-ps5-sony/p/ff8fc4c7ch/ea/fngm/",
        "rating": 5.0,
        "in_stock": true,
        "extracted_at": "2026-02-11T13:03:34-03:00"
    },
    {
        "name": "Fones de ouvido para jogos havit H2002d para PS4, PC, PS5 com som surround",
        "category": "fone",
        "brand": "havit",
        "price": 379.02,
        "product_url": "https://www.magazineluiza.com.br/fones-de-ouvido-para-jogos-havit-h2002d-para-ps4-pc-ps5-com-som-surround/p/dgg9hbj791/ea/hdga/",
        "rating": null,
        "in_stock": true,
        "extracted_at": "2026-02-11T13:03:36-03:00"
    },
    {
        "name": "Fone De Ouvido Bluetooth Waaw By Alok Move 200 30 horas",
        "category": "fone",
        "brand": "WAAW",
        "price": 175.0,
        "product_url": "https://www.magazineluiza.com.br/fone-de-ouvido-bluetooth-waaw-by-alok-move-200-30-horas/p/ec09ebf06h/ea/fngm/",
        "rating": 5.0,
        "in_stock": true,
        "extracted_at": "2026-02-11T13:03:38-03:00"
    },
    {
        "name": "Fone Qcy HT07 ArcBuds Bluetooth 5.2 Cancelamento de Ruídos ANC",
        "category": "fone",
        "brand": "QCY",
        "price": 187.51,
        "product_url": "https://www.magazineluiza.com.br/fone-qcy-ht07-arcbuds-bluetooth-5-2-cancelamento-de-ruidos-anc/p/cha128bddf/ea/fobt/",
        "rating": 4.84,
        "in_stock": true,
        "extracted_at": "2026-02-11T13:03:41-03:00"
    },
    {
        "name": "Fones De Ouvido Sem Fio Bluetooth 5.3 À Prova d'Água Lenovo XT80 Com Redução De Ruído E Microfone",
        "category": "fone",
        "brand": "Lenovo",
        "price": 81.26,
        "product_url": "https://www.magazineluiza.com.br/fones-de-ouvido-sem-fio-bluetooth-5-3-a-prova-d-agua-lenovo-xt80-com-reducao-de-ruido-e-microfone/p/de9887b13h/ea/fobt/",
        "rating": 4.5,
        "in_stock": true,
        "extracted_at": "2026-02-11T13:03:43-03:00"
    },
    {
        "name": "Fone Bluetooth Redmi Buds 6 Play Xiaomi Original",
        "category": "fone",
        "brand": "Xiaomi",
        "price": 189.45,
        "product_url": "https://www.magazineluiza.com.br/fone-bluetooth-redmi-buds-6-play-xiaomi-original/p/gj39k55c36/ea/fobt/",
        "rating": 4.74,
        "in_stock": true,
        "extracted_at": "2026-02-11T13:03:46-03:00"
    },
    {
        "name": "Fones De Ouvido Sem Fio Para Jogos NUBWO G06 Bluetooth 53 Com Microfone Para PS5 PS4 PC Mobile",
        "category": "fone",
        "brand": "NUBWO",
        "price": 196.0,
        "product_url": "https://www.magazineluiza.com.br/fones-de-ouvido-sem-fio-para-jogos-nubwo-g06-bluetooth-53-com-microfone-para-ps5-ps4-pc-mobile/p/hh98j90302/ea/fngm/",
        "rating": null,
        "in_stock": true,
        "extracted_at": "2026-02-11T13:03:48-03:00"
    },
    {
        "name": "Fone De Ouvido Sem Fio Bluetooth 5.1 Compativel com Samsung Iphone Motorola Xiaomi Huawei LG 770-771",
        "category": "fone",
        "brand": "Kaidi",
        "price": 99.9,
        "product_url": "https://www.magazineluiza.com.br/fone-de-ouvido-sem-fio-bluetooth-5-1-compativel-com-samsung-iphone-motorola-xiaomi-huawei-lg-770-771-kaidi/p/hkje8jc8ka/ea/fobt/",
        "rating": 4.79,
        "in_stock": true,
        "extracted_at": "2026-02-11T13:03:51-03:00"
    },
    {
        "name": "Fones De Ouvido Esportivos Sem Fio Lenovo LP75 Bluetooth 5.3 TWS Hifi Stereo Sound LED Power Display",
        "category": "fone",
        "brand": "Lenovo",
        "price": 70.0,
        "product_url": "https://www.magazineluiza.com.br/fones-de-ouvido-esportivos-sem-fio-lenovo-lp75-bluetooth-5-3-tws-hifi-stereo-sound-led-power-display/p/hjh8b9kea3/ea/fobt/",
        "rating": null,
        "in_stock": true,
        "extracted_at": "2026-02-11T13:03:53-03:00"
    },
    {
        "name": "Fone de Ouvido JBL Tune 310C, USB-C, Azul - 28913775",
        "category": "fone",
        "brand": "JBL",
        "price": 99.0,
        "product_url": "https://www.magazineluiza.com.br/fone-de-ouvido-jbl-tune-310c-usb-c-azul-28913775/p/edfg08547j/ea/focf/",
        "rating": 4.6,
        "in_stock": true,
        "extracted_at": "2026-02-11T13:03:55-03:00"
    },
    {
        "name": "Fone Gatinho Sem Fio Led Bluetooth Infantil Orelha Gato Cat - Laves",
        "category": "fone",
        "brand": null,
        "price": 41.0,
        "product_url": "https://www.magazineluiza.com.br/fone-gatinho-sem-fio-led-bluetooth-infantil-orelha-gato-cat-laves/p/hh84c87kb6/ea/hebl/",
        "rating": 5.0,
        "in_stock": true,
        "extracted_at": "2026-02-11T13:03:57-03:00"
    },
    {
        "name": "Fones De Ouvido Com Tradução AI Em 144 Idiomas Tradutores De Voz Em Tempo Real Para Viagens,",
        "category": "fone",
        "brand": "DAMORE",
        "price": 26.03,
        "product_url": "https://www.magazineluiza.com.br/fones-de-ouvido-com-traducao-ai-em-144-idiomas-tradutores-de-voz-em-tempo-real-para-viagens-damore/p/dj570d3g3e/ea/fobt/",
        "rating": 1.0,
        "in_stock": true,
        "extracted_at": "2026-02-11T13:03:59-03:00"
    },
    {
        "name": "Fone de Ouvido Gamer JBL Quantum 50N, Azul e Vermelho - 28913839",
        "category": "fone",
        "brand": "JBL",
        "price": 112.0,
        "product_url": "https://www.magazineluiza.com.br/fone-de-ouvido-gamer-jbl-quantum-50n-azul-e-vermelho-28913839/p/fjjf883h18/ea/focf/",
        "rating": 4.7,
        "in_stock": true,
        "extracted_at": "2026-02-11T13:04:01-03:00"
    },
    {
        "name": "Fone de Ouvido Bluetooth sem Fio Headset Anti-ruído Original Inova",
        "category": "fone",
        "brand": "Inova",
        "price": 66.67,
        "product_url": "https://www.magazineluiza.com.br/fone-de-ouvido-bluetooth-sem-fio-headset-anti-ruido-original-inova/p/ab7g167h42/ea/hdgm/",
        "rating": 4.56,
        "in_stock": true,
        "extracted_at": "2026-02-11T13:04:04-03:00"
    },
    {
        "name": "Fones De Ouvido Lenovo GM2 pro TWS Bluetooth 5.3 Com Modos Duplos, Chamadas HD E 2 Microfones",
        "category": "fone",
        "brand": "Lenovo",
        "price": 38.95,
        "product_url": "https://www.magazineluiza.com.br/fones-de-ouvido-lenovo-gm2-pro-tws-bluetooth-5-3-com-modos-duplos-chamadas-hd-e-2-microfones/p/bahbggag05/ea/fobt/",
        "rating": 5.0,
        "in_stock": true,
        "extracted_at": "2026-02-11T13:04:06-03:00"
    },
    {
        "name": "Samsung Galaxy Buds Core Branco Fone de Ouvido Sem Fio Cancelamento de Ruído Interprete inteligente",
        "category": "fone",
        "brand": "SAMSUNG",
        "price": 258.99,
        "product_url": "https://www.magazineluiza.com.br/samsung-galaxy-buds-core-branco-fone-de-ouvido-sem-fio-cancelamento-de-ruido-interprete-inteligente/p/hhg379kkeh/ea/eafn/",
        "rating": 4.77,
        "in_stock": true,
        "extracted_at": "2026-02-11T13:04:08-03:00"
    },
    {
        "name": "Fone De Ouvido Bluetooth Sem Fio JBL Wave Buds 2 - Preto",
        "category": "fone",
        "brand": "JBL",
        "price": 278.1,
        "product_url": "https://www.magazineluiza.com.br/fone-de-ouvido-bluetooth-sem-fio-jbl-wave-buds-2-preto/p/ddbk512eja/ea/fobt/",
        "rating": 4.71,
        "in_stock": true,
        "extracted_at": "2026-02-11T13:04:11-03:00"
    },
    {
        "name": "Fone de Ouvido Sem Fio JBL Tune Flex, Bluetooth, Branco - 28913853",
        "category": "fone",
        "brand": "JBL",
        "price": 448.9,
        "product_url": "https://www.magazineluiza.com.br/fone-de-ouvido-sem-fio-jbl-tune-flex-bluetooth-branco-28913853/p/kgga57fb3e/ea/fobt/",
        "rating": 5.0,
        "in_stock": true,
        "extracted_at": "2026-02-11T13:04:13-03:00"
    },
    {
        "name": "Fone de Ouvido Sem Fio QCY T1C TWS Bluetooth 5.1 Case 380 mAh",
        "category": "fone",
        "brand": "QCY",
        "price": 130.38,
        "product_url": "https://www.magazineluiza.com.br/fone-de-ouvido-sem-fio-qcy-t1c-tws-bluetooth-5-1-case-380-mah/p/ab01je8hgj/ea/fobt/",
        "rating": 4.67,
        "in_stock": true,
        "extracted_at": "2026-02-11T13:04:16-03:00"
    },
    {
        "name": "Fone de Ouvido Bluetooth Sem Fio Junior 320BT JBL - Azul - 28913833",
        "category": "fone",
        "brand": "JBL",
        "price": 199.0,
        "product_url": "https://www.magazineluiza.com.br/fone-de-ouvido-bluetooth-sem-fio-junior-320bt-jbl-azul-28913833/p/je1ae1bbch/ea/fobt/",
        "rating": 3.5,
        "in_stock": true,
        "extracted_at": "2026-02-11T13:04:18-03:00"
    },
    {
        "name": "Fone De Ouvido Sem Fio Baseus Bowie E20 Bluetooth 5.3",
        "category": "fone",
        "brand": "Baseus",
        "price": 143.0,
        "product_url": "https://www.magazineluiza.com.br/fone-de-ouvido-sem-fio-baseus-bowie-e20-bluetooth-5-3/p/cccga1kddg/ea/focf/",
        "rating": 4.5,
        "in_stock": true,
        "extracted_at": "2026-02-11T13:04:20-03:00"
    },
    {
        "name": "Fone de Ouvido Bluetooth Cancelamento de Ruído Bateria Longa Duração - Basike",
        "category": "fone",
        "brand": "Basike",
        "price": 206.0,
        "product_url": "https://www.magazineluiza.com.br/fone-de-ouvido-bluetooth-cancelamento-de-ruido-bateria-longa-duracao-basike/p/hba7d09hj7/ea/fobt/",
        "rating": null,
        "in_stock": true,
        "extracted_at": "2026-02-11T13:04:23-03:00"
    },
    {
        "name": "Fone de Ouvido Gamer Warrior com Microfone",
        "category": "fone",
        "brand": "Warrior",
        "price": 94.91,
        "product_url": "https://www.magazineluiza.com.br/fone-de-ouvido-gamer-warrior-com-microfone-notebook-ps4-xbox-one-intra-auricular/p/227762000/ea/fngm/",
        "rating": 5.0,
        "in_stock": true,
        "extracted_at": "2026-02-11T13:04:25-03:00"
    },
    {
        "name": "Fone de Ouvido Bluetooth QCY MeloBuds HT05 ANC",
        "category": "fone",
        "brand": "QCY",
        "price": 267.89,
        "product_url": "https://www.magazineluiza.com.br/fone-de-ouvido-bluetooth-qcy-melobuds-ht05-anc/p/faekdb4hke/ea/fobt/",
        "rating": 4.84,
        "in_stock": true,
        "extracted_at": "2026-02-11T13:04:28-03:00"
    },
    {
        "name": "Fone De Ouvido Bluetooth Sem Fio JBL Tune 720BT Dobrável - Preto",
        "category": "fone",
        "brand": "JBL",
        "price": 389.0,
        "product_url": "https://www.magazineluiza.com.br/fone-de-ouvido-bluetooth-sem-fio-jbl-tune-720bt-dobravel-preto/p/jebe8c3b4j/ea/fobt/",
        "rating": 4.8,
        "in_stock": true,
        "extracted_at": "2026-02-11T13:04:30-03:00"
    },
    {
        "name": "Fone de Ouvido Bluetooth Lenovo LP75 TWS - À Prova D'Água, com Redução de Ruído e Som HiFi",
        "category": "fone",
        "brand": "Lenovo",
        "price": 81.11,
        "product_url": "https://www.magazineluiza.com.br/fone-de-ouvido-bluetooth-lenovo-lp75-tws-a-prova-d-agua-com-reducao-de-ruido-e-som-hifi/p/jdh0h0dkkh/ea/fobt/",
        "rating": 4.62,
        "in_stock": true,
        "extracted_at": "2026-02-11T13:04:32-03:00"
    },
    {
        "name": "Fone Bluetooth QCY T13 ANC Cancelamento de Ruído Ativo 5.3",
        "category": "fone",
        "brand": "QCY",
        "price": 169.86,
        "product_url": "https://www.magazineluiza.com.br/fone-bluetooth-qcy-t13-anc-cancelamento-de-ruido-ativo-5-3/p/hgh959ekkb/ea/fobt/",
        "rating": 4.73,
        "in_stock": true,
        "extracted_at": "2026-02-11T13:04:35-03:00"
    },
    {
        "name": "Fone de Ouvido Bluetooth Headphone Sem Fio Philips TAH1205BK 00 - Preto",
        "category": "fone",
        "brand": "PHILIPS",
        "price": 214.17,
        "product_url": "https://www.magazineluiza.com.br/fone-de-ouvido-bluetooth-headphone-sem-fio-philips-tah1205bk-00-preto/p/cejb2b0hbk/ea/fobt/",
        "rating": 4.69,
        "in_stock": true,
        "extracted_at": "2026-02-11T13:04:37-03:00"
    },
    {
        "name": "Fone de Ouvido Bluetooth 5.4 TWS com Cancelamento de Ruído e Microfone - Basike",
        "category": "fone",
        "brand": "Basike",
        "price": 67.0,
        "product_url": "https://www.magazineluiza.com.br/fone-de-ouvido-bluetooth-5-4-tws-com-cancelamento-de-ruido-e-microfone-basike/p/ef4gkh4ge4/ea/hebl/",
        "rating": null,
        "in_stock": true,
        "extracted_at": "2026-02-11T13:04:40-03:00"
    },
    {
        "name": "Fone Bluetooth Redmi Buds 6 Play Xiaomi Original",
        "category": "fone",
        "brand": "Xiaomi",
        "price": 189.45,
        "product_url": "https://www.magazineluiza.com.br/fone-bluetooth-redmi-buds-6-play-xiaomi-original/p/kc1a483be7/ea/fobt/",
        "rating": 4.74,
        "in_stock": true,
        "extracted_at": "2026-02-11T13:04:42-03:00"
    },
    {
        "name": "Fone de Ouvido Bluetooth Sem Fio Inova Original Headphone Wireless",
        "category": "fone",
        "brand": "Inova",
        "price": 67.85,
        "product_url": "https://www.magazineluiza.com.br/fone-de-ouvido-bluetooth-sem-fio-inova-original-headphone-wireless/p/chf8b3f3gg/ea/hebl/",
        "rating": 4.52,
        "in_stock": true,
        "extracted_at": "2026-02-11T13:04:44-03:00"
    },
    {
        "name": "Fones de ouvido True Wireless SAMSUNG Galaxy Buds2 com cancelamento de ruído",
        "category": "fone",
        "brand": "SAMSUNG",
        "price": 1628.27,
        "product_url": "https://www.magazineluiza.com.br/fones-de-ouvido-true-wireless-samsung-galaxy-buds2-com-cancelamento-de-ruido/p/ccc5k4ggb1/ea/gabu/",
        "rating": null,
        "in_stock": true,
        "extracted_at": "2026-02-11T13:04:47-03:00"
    },
    {
        "name": "Fone de Ouvido Apple Beats Flex, In Ear, Preto - MYMC2BE/A",
        "category": "fone",
        "brand": "Beats",
        "price": 429.0,
        "product_url": "https://www.magazineluiza.com.br/fone-de-ouvido-apple-beats-flex-in-ear-preto-mymc2be-a/p/cch42174dh/ea/fobt/",
        "rating": 3.25,
        "in_stock": true,
        "extracted_at": "2026-02-11T13:04:49-03:00"
    },
    {
        "name": "Fone De Ouvido Headphone BH470 - BEHRINGER",
        "category": "fone",
        "brand": "BEHRINGER",
        "price": 350.0,
        "product_url": "https://www.magazineluiza.com.br/fone-de-ouvido-headphone-bh470-behringer/p/jgjkd2fe11/ea/hefi/",
        "rating": 5.0,
        "in_stock": true,
        "extracted_at": "2026-02-11T13:04:52-03:00"
    },
    {
        "name": "Fone de Ouvido sem Fio Moto Buds Loop by Bose",
        "category": "fone",
        "brand": "Motorola",
        "price": 599.0,
        "product_url": "https://www.magazineluiza.com.br/fone-de-ouvido-sem-fio-moto-buds-loop-by-bose-motorola/p/dbka780g3a/ea/focf/",
        "rating": 4.67,
        "in_stock": true,
        "extracted_at": "2026-02-11T13:04:55-03:00"
    },
    {
        "name": "Fones de Ouvido Sem Fio Sony WH-CH720N com Cancelamento de Ruído - Pretos",
        "category": "fone",
        "brand": "Sony",
        "price": 869.0,
        "product_url": "https://www.magazineluiza.com.br/fones-de-ouvido-sem-fio-sony-wh-ch720n-com-cancelamento-de-ruido-pretos/p/be0caj2bf8/ea/fobt/",
        "rating": null,
        "in_stock": true,
        "extracted_at": "2026-02-11T13:04:57-03:00"
    },
    {
        "name": "Fones De Ouvido Esportivos Lenovo Thinkplus XT62 Bluetooth 5.3 À Prova d'Água Com Controle Por Toque",
        "category": "fone",
        "brand": "Lenovo",
        "price": 68.0,
        "product_url": "https://www.magazineluiza.com.br/fones-de-ouvido-esportivos-lenovo-thinkplus-xt62-bluetooth-5-3-a-prova-d-agua-com-controle-por-toque/p/ajakaa744a/ea/hebh/",
        "rating": null,
        "in_stock": true,
        "extracted_at": "2026-02-11T13:05:00-03:00"
    },
    {
        "name": "Fones De Ouvido Bluetooth Sem Fio Lenovo XT88, Fones De Música Hifi Com Microfone, Headset Esportivo",
        "category": "fone",
        "brand": "Lenovo",
        "price": 64.0,
        "product_url": "https://www.magazineluiza.com.br/fones-de-ouvido-bluetooth-sem-fio-lenovo-xt88-fones-de-musica-hifi-com-microfone-headset-esportivo/p/db2fc5fhgd/ea/hebl/",
        "rating": null,
        "in_stock": true,
        "extracted_at": "2026-02-11T13:05:02-03:00"
    },
    {
        "name": "Fone Bluetooth TWS Galaxy Buds3, Cinza, SM-R530NZAAZTO, SAMSUNG  SAMSUNG",
        "category": "fone",
        "brand": "SAMSUNG",
        "price": 1105.65,
        "product_url": "https://www.magazineluiza.com.br/fone-bluetooth-tws-galaxy-buds3-cinza-sm-r530nzaazto-samsung-samsung/p/jak19abj4b/ea/gabu/",
        "rating": 4.3,
        "in_stock": true,
        "extracted_at": "2026-02-11T13:05:04-03:00"
    },
    {
        "name": "Fone de Ouvido Bluetooth AKG Y500 com Microfone Preto",
        "category": "fone",
        "brand": "AKG",
        "price": 449.1,
        "product_url": "https://www.magazineluiza.com.br/fone-de-ouvido-bluetooth-akg-y500-com-microfone-preto/p/224331200/ea/eafn/",
        "rating": 4.75,
        "in_stock": true,
        "extracted_at": "2026-02-11T13:05:07-03:00"
    },
    {
        "name": "Fone De Ouvido Gatinho Bluetooth Rosa Led Feminina Infantil - Laves",
        "category": "fone",
        "brand": null,
        "price": 41.0,
        "product_url": "https://www.magazineluiza.com.br/fone-de-ouvido-gatinho-bluetooth-rosa-led-feminina-infantil-laves/p/gk2k34e8c9/ea/hebl/",
        "rating": 5.0,
        "in_stock": true,
        "extracted_at": "2026-02-11T13:05:09-03:00"
    },
    {
        "name": "Fone Ouvido Tune 510 BT JBL Bluetooth c/ Microfone Branco",
        "category": "fone",
        "brand": "JBL",
        "price": 267.12,
        "product_url": "https://www.magazineluiza.com.br/fone-ouvido-tune-510-bt-jbl-bluetooth-c-microfone-branco/p/gajejf6fkb/ea/fobt/",
        "rating": 4.86,
        "in_stock": true,
        "extracted_at": "2026-02-11T13:05:12-03:00"
    },
    {
        "name": "Fone de Ouvido Bluetooth Anker Soundcore SPACE A40 Earbuds Cancelamento de Ruidos Preto - SPACE A40",
        "category": "fone",
        "brand": "Anker",
        "price": 416.66,
        "product_url": "https://www.magazineluiza.com.br/fone-de-ouvido-bluetooth-anker-soundcore-space-a40-earbuds-cancelamento-de-ruidos-preto-space-a40/p/ek0aag101f/ea/eafn/",
        "rating": 5.0,
        "in_stock": true,
        "extracted_at": "2026-02-11T13:05:14-03:00"
    },
    {
        "name": "Fone de Ouvido Bluetooth Sem Fio Inova Original Headphone Wireless",
        "category": "fone",
        "brand": "Inova",
        "price": 67.85,
        "product_url": "https://www.magazineluiza.com.br/fone-de-ouvido-bluetooth-sem-fio-inova-original-headphone-wireless/p/bdghfg80a1/ea/hebl/",
        "rating": 4.52,
        "in_stock": true,
        "extracted_at": "2026-02-11T13:05:16-03:00"
    },
    {
        "name": "Fones de ouvido Beats Solo4 Cloud Pink com AppleCare+ 2 anos",
        "category": "fone",
        "brand": "Beats",
        "price": 1444.14,
        "product_url": "https://www.magazineluiza.com.br/fones-de-ouvido-beats-solo4-cloud-pink-com-applecare-2-anos/p/bhfj69aefj/ea/fobt/",
        "rating": null,
        "in_stock": true,
        "extracted_at": "2026-02-11T13:05:18-03:00"
    },
    {
        "name": "Fone de Ouvido Bluetooth sem Fio Headset Anti-ruído Original Inova",
        "category": "fone",
        "brand": "Inova",
        "price": 66.67,
        "product_url": "https://www.magazineluiza.com.br/fone-de-ouvido-bluetooth-sem-fio-headset-anti-ruido-original-inova/p/decefk0ee9/ea/hdgm/",
        "rating": 4.56,
        "in_stock": true,
        "extracted_at": "2026-02-11T13:05:20-03:00"
    },
    {
        "name": "Fones de ouvido Bluetooth SAMSUNG Galaxy Buds 3 Pro AI Silver US",
        "category": "fone",
        "brand": "SAMSUNG",
        "price": 1774.0,
        "product_url": "https://www.magazineluiza.com.br/fones-de-ouvido-bluetooth-samsung-galaxy-buds-3-pro-ai-silver-us/p/jg599a1e5h/ea/gabu/",
        "rating": null,
        "in_stock": true,
        "extracted_at": "2026-02-11T13:05:22-03:00"
    },
    {
        "name": "Fone de ouvido Tipo-c compatível Samsung S20 FE",
        "category": "fone",
        "brand": "Premium",
        "price": 27.09,
        "product_url": "https://www.magazineluiza.com.br/fone-de-ouvido-tipo-c-compativel-samsung-s20-fe-premium/p/ae8k1c03h0/ea/focf/",
        "rating": 4.37,
        "in_stock": true,
        "extracted_at": "2026-02-11T13:05:25-03:00"
    },
    {
        "name": "Fone de Ouvido Beats Studio Pro, Wirelless, Bluetooth, Até 40hr, USB-C, Marrom - MQTT3BE/A",
        "category": "fone",
        "brand": "Beats",
        "price": 1893.0,
        "product_url": "https://www.magazineluiza.com.br/fone-de-ouvido-beats-studio-pro-wirelless-bluetooth-ate-40hr-usb-c-marrom-mqtt3be-a/p/jhdah9j63c/ea/fobt/",
        "rating": null,
        "in_stock": true,
        "extracted_at": "2026-02-11T13:05:27-03:00"
    },
    {
        "name": "Fone de Ouvido JBL Tour Pro 3, Bluetooth 5.3, Smart Charging Case, Cancelamento de ruído, Até 44 horas de bateria, Preto - JBLTOURPRO3BLK",
        "category": "fone",
        "brand": "JBL",
        "price": 1669.0,
        "product_url": "https://www.magazineluiza.com.br/fone-de-ouvido-jbl-tour-pro-3-bluetooth-5-3-smart-charging-case-cancelamento-de-ruido-ate-44-horas-de-bateria-preto-jbltourpro3blk/p/ebd92a8edh/ea/fobt/",
        "rating": 5.0,
        "in_stock": true,
        "extracted_at": "2026-02-11T13:05:29-03:00"
    },
    {
        "name": "Fone de Ouvido Intra Auricular Bluetooth WAAW MOB 500W ANC Cancelamento de Ruído Bateria Longa Duração Modo Gamer, IPX4, Controle Touch",
        "category": "fone",
        "brand": "WAAW",
        "price": 279.9,
        "product_url": "https://www.magazineluiza.com.br/fone-de-ouvido-intra-auricular-bluetooth-waaw-mob-500w-anc-cancelamento-de-ruido-bateria-longa-duracao-modo-gamer-ipx4-controle-touch/p/ea6kfah1a7/ea/fobt/",
        "rating": 5.0,
        "in_stock": true,
        "extracted_at": "2026-02-11T13:05:32-03:00"
    },
    {
        "name": "Fone de Ouvido QCY HT10 AilyBuds Pro ANC Bluetooth 5.3 Multiponto",
        "category": "fone",
        "brand": "QCY",
        "price": 289.85,
        "product_url": "https://www.magazineluiza.com.br/fone-de-ouvido-qcy-ht10-ailybuds-pro-anc-bluetooth-5-3-multiponto/p/dh40kj8ge4/ea/fngm/",
        "rating": 5.0,
        "in_stock": true,
        "extracted_at": "2026-02-11T13:05:35-03:00"
    },
    {
        "name": "Fone De Ouvido Sem Fio Huawei Freeclip Tws Com Microfone",
        "category": "fone",
        "brand": "Huawei",
        "price": 1099.0,
        "product_url": "https://www.magazineluiza.com.br/fone-de-ouvido-sem-fio-huawei-freeclip-tws-com-microfone/p/gb0b3e0536/ea/fobt/",
        "rating": 5.0,
        "in_stock": true,
        "extracted_at": "2026-02-11T13:05:37-03:00"
    },
    {
        "name": "Fone de Ouvido Bluetooth 5.4 TWS Intra Auricular som Anti ruído Original Basike",
        "category": "fone",
        "brand": "Basike",
        "price": 163.0,
        "product_url": "https://www.magazineluiza.com.br/fone-de-ouvido-bluetooth-5-4-tws-intra-auricular-som-anti-ruido-original-basike/p/kea2496090/ea/fobt/",
        "rating": null,
        "in_stock": true,
        "extracted_at": "2026-02-11T13:05:40-03:00"
    },
    {
        "name": "Fone de ouvido Razer Kraken Kitty V2 BT sem fio RGB Bluetooth 5.2",
        "category": "fone",
        "brand": "Razer",
        "price": 1315.6,
        "product_url": "https://www.magazineluiza.com.br/fone-de-ouvido-razer-kraken-kitty-v2-bt-sem-fio-rgb-bluetooth-5-2/p/jc0bge3k04/ea/fngm/",
        "rating": null,
        "in_stock": true,
        "extracted_at": "2026-02-11T13:05:43-03:00"
    },
    {
        "name": "Fone de Ouvido Gamer Corsair VOID RGB ELITE Wireless - Branco",
        "category": "fone",
        "brand": "Corsair",
        "price": 1049.2,
        "product_url": "https://www.magazineluiza.com.br/fone-de-ouvido-gamer-corsair-void-rgb-elite-wireless-branco/p/hhb05k5d49/ea/hdga/",
        "rating": 4.2,
        "in_stock": true,
        "extracted_at": "2026-02-11T13:05:45-03:00"
    },
    {
        "name": "Fone Ouvido Bluetooth IA T68 Tradução Simultânea Awei Sem Fio Cancelamento Ruido",
        "category": "fone",
        "brand": "Awei",
        "price": 131.96,
        "product_url": "https://www.magazineluiza.com.br/fone-ouvido-bluetooth-ia-t68-traducao-simultanea-awei-sem-fio-cancelamento-ruido/p/dc29620f66/ea/fngm/",
        "rating": null,
        "in_stock": true,
        "extracted_at": "2026-02-11T13:05:47-03:00"
    },
    {
        "name": "Fone Qcy T29 Bluetooth 5.3 IPX4 Cancelamento Enc",
        "category": "fone",
        "brand": "QCY",
        "price": 155.57,
        "product_url": "https://www.magazineluiza.com.br/fone-qcy-t29-bluetooth-5-3-ipx4-cancelamento-enc/p/ek1jb69421/ea/fobt/",
        "rating": 4.76,
        "in_stock": true,
        "extracted_at": "2026-02-11T13:05:50-03:00"
    },
    {
        "name": "Fone de Ouvido Bluetooth Sem Fio Inova Original Headphone Wireless",
        "category": "fone",
        "brand": "Inova",
        "price": 71.58,
        "product_url": "https://www.magazineluiza.com.br/fone-de-ouvido-bluetooth-sem-fio-inova-original-headphone-wireless/p/df3d42a97a/ea/hebl/",
        "rating": 4.52,
        "in_stock": true,
        "extracted_at": "2026-02-11T13:05:52-03:00"
    },
    {
        "name": "Fones de ouvido Bluetooth Soundcore Anker Life Q30 Blue",
        "category": "fone",
        "brand": "Soundcore",
        "price": 679.67,
        "product_url": "https://www.magazineluiza.com.br/fones-de-ouvido-bluetooth-soundcore-anker-life-q30-blue/p/eh2hcgce75/ea/fobt/",
        "rating": null,
        "in_stock": true,
        "extracted_at": "2026-02-11T13:05:55-03:00"
    },
    {
        "name": "Fones de ouvido Bluetooth Disney Mickey Mouse com estojo de carregamento - Fone de ouvido sem fio Bluetooth com microfone embutido e 30 horas de diversão - Disneyland Essentials e presentes Disney para mulheres e homens de todas as idades - iJoy",
        "category": "fone",
        "brand": "iJoy",
        "price": 312.77,
        "product_url": "https://www.magazineluiza.com.br/fones-de-ouvido-bluetooth-disney-mickey-mouse-com-estojo-de-carregamento-fone-de-ouvido-sem-fio-bluetooth-com-microfone-embutido-e-30-horas-de-diversao-disneyland-essentials-e-presentes-disney-para-mulheres-e-homens-de-todas-as-idades-ijoy/p/fjd40je765/ea/fobt/",
        "rating": null,
        "in_stock": true,
        "extracted_at": "2026-02-11T13:05:57-03:00"
    }
]